zymouse/__init__.py
zymouse/bs/Bs.py
zymouse/bs/__init__.py
zymouse-19.2.20.dist-info/METADATA
zymouse-19.2.20.dist-info/WHEEL
zymouse-19.2.20.dist-info/top_level.txt
zymouse-19.2.20.dist-info/RECORD
