Metadata-Version: 2.1
Name: zymouse
Version: 19.2.20
Summary: This is my collection bag.
Home-page: https://github.com/zymouse/zymouse
Author: zymouse
Author-email: mouse_zy@qq.com
License: MIT Licence
Platform: window10
Classifier: Programming Language :: Python :: 3
Classifier: License :: OSI Approved :: MIT License
Classifier: Operating System :: OS Independent
